{
  "users": [
    {
      "id": "1",
      "name": "Javier",
      "last_name": "Martin",
      "email": "j.com",
      "password": "javi",
      "city": "Almeria",
      "gender": "mal",
      "profilePicture": "https://avataaars.io/?accessoriesType=Prescription01&avatarStyle=Circle&clotheColor=PastelYellow&clotheType=Overall&eyeType=WinkWacky&eyebrowType=Default&facialHairColor=Blonde&facialHairType=BeardLight&hairColor=Auburn&hatColor=Black&mouthType=Disbelief&skinColor=Pale&topType=Hijab",
      "country": "Spain",
      "dateOfBirth": "1997-11-12",
      "likedSongs": []
    },
    {
      "id": "2",
      "name": "Lucia",
      "last_name": "Mercorelli",
      "email": "lucia@lucia.com",
      "password": "lucialucia",
      "city": "Barcelona",
      "gender": "Female",
      "profilePicture": "",
      "country": "Spain",
      "dateOfBirth": "1982-12-16",
      "likedSongs": []
    },
    {
      "id": "3",
      "name": "Eira",
      "last_name": "Melè",
      "email": "eira@eira.com",
      "password": "eiraeira",
      "city": "Barcelona",
      "gender": "Female",
      "profilePicture": "",
      "country": "Spain",
      "dateOfBirth": "1986-06-25",
      "likedSongs": []
    },
    {
      "id": "4",
      "name": "Alvaro",
      "last_name": "del Cacho",
      "email": "alvaro@alvaro.com",
      "password": "alvaroalvaro",
      "city": "Valencia",
      "gender": "Male",
      "profilePicture": "",
      "country": "Spain",
      "dateOfBirth": "1999-11-18",
      "likedSongs": []
    },
    {
      "id": "5",
      "name": "Ander",
      "last_name": "Aldabaldetreku",
      "email": "ander@ander.com",
      "password": "anderander",
      "city": "Orio",
      "gender": "malote",
      "profilePicture": "",
      "country": "Spain",
      "dateOfBirth": "1987-07-03",
      "likedSongs": [
        2,
        3,
        4,
        8
      ]
    },
    {
      "id": "6",
      "name": "Ariadna",
      "last_name": "Melé",
      "email": "ariadna@ariadna.com",
      "password": "ariadnaariadna",
      "city": "Barcelona",
      "gender": "Female",
      "profilePicture": "",
      "country": "Spain",
      "dateOfBirth": "2020-04-27",
      "likedSongs": []
    },
    {
      "id": "7",
      "name": "Jose",
      "last_name": "Enrique",
      "email": "enrique@enrique.com",
      "password": "enriqueenrique",
      "city": "malos aires",
      "gender": "tiburon",
      "profilePicture": "",
      "country": "Spain",
      "dateOfBirth": "2024-03-10",
      "likedSongs": []
    },
    {
      "id": "8",
      "name": "mikel",
      "last_name": "mikel",
      "email": "mikel@mikel.com",
      "password": "mikelmikel",
      "city": "mikel",
      "gender": "raton",
      "profilePicture": "https://avataaars.io/?accessoriesType=Prescription01&avatarStyle=Circle&clotheColor=PastelYellow&clotheType=Overall&eyeType=WinkWacky&eyebrowType=Default&facialHairColor=Blonde&facialHairType=BeardLight&hairColor=Auburn&hatColor=Black&mouthType=Disbelief&skinColor=Pale&topType=Hijab",
      "country": "mikel",
      "dateOfBirth": "2024-03-12",
      "likedSongs": []
    }
  ]
}